Metadata-Version: 1.1
Name: cuid.py
Version: 0.2
Summary: Fast, scalable unique ID generation
Home-page: http://github.com/necaris/cuid.py
Author: Rami Chowdhury
Author-email: rami.chowdhury@gmail.com
License: UNKNOWN
Download-URL: http://github.com/necaris/cuid.py/tarball/v0.2
Platform: UNKNOWN
Classifier: Development Status :: 4 - Beta
Classifier: Intended Audience :: Developers
Classifier: License :: OSI Approved :: Apache Software License
Classifier: Operating System :: POSIX
Classifier: Programming Language :: Python
Classifier: Programming Language :: Python :: 3
Classifier: Topic :: Internet :: WWW/HTTP
Classifier: Topic :: Software Development :: Libraries :: Python Modules
